{"ESSER": {"IIIII": [], "IIIIM": [], "IIIIC": [], "IIIMI": [], "IIIMM": [], "IIIMC": [], "IIICI": [], "IIICM": [], "IIICC": [], "IIMII": [], "IIMIM": [], "IIMIC": [], "IIMMI": [], "IIMMM": [], "IIMMC": [], "IIMCI": [], "IIMCM": [], "IIMCC": [], "IICII": [], "IICIM": [], "IICIC": [], "IICMI": [], "IICMM": [], "IICMC": [], "IICCI": [], "IICCM": [], "IICCC": [], "IMIII": [], "IMIIM": [], "IMIIC": [], "IMIMI": [], "IMIMM": [], "IMIMC": [], "IMICI": [], "IMICM": [], "IMICC": [], "IMMII": [], "IMMIM": [], "IMMIC": [], "IMMMI": [], "IMMMM": [], "IMMMC": [], "IMMCI": [], "IMMCM": [], "IMMCC": [], "IMCII": [], "IMCIM": [], "IMCIC": [], "IMCMI": [], "IMCMM": [], "IMCMC": [], "IMCCI": [], "IMCCM": [], "IMCCC": [], "ICIII": [], "ICIIM": [], "ICIIC": [], "ICIMI": [], "ICIMM": [], "ICIMC": [], "ICICI": [], "ICICM": [], "ICICC": [], "ICMII": [], "ICMIM": [], "ICMIC": [], "ICMMI": [], "ICMMM": [], "ICMMC": [], "ICMCI": [], "ICMCM": [], "ICMCC": [], "ICCII": [], "ICCIM": [], "ICCIC": [], "ICCMI": [], "ICCMM": [], "ICCMC": [], "ICCCI": [], "ICCCM": [], "ICCCC": [], "MIIII": [], "MIIIM": [], "MIIIC": [], "MIIMI": [], "MIIMM": [], "MIIMC": [], "MIICI": [], "MIICM": [], "MIICC": [], "MIMII": [], "MIMIM": [], "MIMIC": [], "MIMMI": [], "MIMMM": [], "MIMMC": [], "MIMCI": [], "MIMCM": [], "MIMCC": [], "MICII": [], "MICIM": [], "MICIC": [], "MICMI": [], "MICMM": [], "MICMC": [], "MICCI": [], "MICCM": [], "MICCC": [], "MMIII": [], "MMIIM": [], "MMIIC": [], "MMIMI": [], "MMIMM": [], "MMIMC": [], "MMICI": [], "MMICM": [], "MMICC": [], "MMMII": [], "MMMIM": [], "MMMIC": [], "MMMMI": ["SENSE"], "MMMMM": [], "MMMMC": [], "MMMCI": ["SENES"], "MMMCM": [], "MMMCC": [], "MMCII": [], "MMCIM": [], "MMCIC": [], "MMCMI": [], "MMCMM": [], "MMCMC": [], "MMCCI": [], "MMCCM": [], "MMCCC": [], "MCIII": [], "MCIIM": [], "MCIIC": [], "MCIMI": [], "MCIMM": [], "MCIMC": [], "MCICI": [], "MCICM": [], "MCICC": [], "MCMII": [], "MCMIM": [], "MCMIC": [], "MCMMI": [], "MCMMM": [], "MCMMC": [], "MCMCI": [], "MCMCM": [], "MCMCC": [], "MCCII": [], "MCCIM": [], "MCCIC": [], "MCCMI": [], "MCCMM": [], "MCCMC": [], "MCCCI": [], "MCCCM": [], "MCCCC": [], "CIIII": [], "CIIIM": [], "CIIIC": [], "CIIMI": [], "CIIMM": [], "CIIMC": [], "CIICI": [], "CIICM": [], "CIICC": [], "CIMII": [], "CIMIM": [], "CIMIC": [], "CIMMI": [], "CIMMM": [], "CIMMC": [], "CIMCI": [], "CIMCM": [], "CIMCC": [], "CICII": [], "CICIM": [], "CICIC": [], "CICMI": [], "CICMM": [], "CICMC": [], "CICCI": [], "CICCM": [], "CICCC": [], "CMIII": [], "CMIIM": [], "CMIIC": [], "CMIMI": [], "CMIMM": [], "CMIMC": [], "CMICI": [], "CMICM": [], "CMICC": [], "CMMII": [], "CMMIM": [], "CMMIC": [], "CMMMI": [], "CMMMM": [], "CMMMC": [], "CMMCI": [], "CMMCM": [], "CMMCC": [], "CMCII": [], "CMCIM": [], "CMCIC": [], "CMCMI": [], "CMCMM": [], "CMCMC": [], "CMCCI": [], "CMCCM": [], "CMCCC": [], "CCIII": [], "CCIIM": [], "CCIIC": [], "CCIMI": [], "CCIMM": [], "CCIMC": [], "CCICI": [], "CCICM": [], "CCICC": [], "CCMII": [], "CCMIM": [], "CCMIC": [], "CCMMI": [], "CCMMM": [], "CCMMC": [], "CCMCI": ["ESPES", "ESTES"], "CCMCM": [], "CCMCC": [], "CCCII": [], "CCCIM": [], "CCCIC": [], "CCCMI": [], "CCCMM": [], "CCCMC": [], "CCCCI": [], "CCCCM": [], "CCCCC": ["ESSER"]}, "VEURE": {"IIIII": [], "IIIIM": [], "IIIIC": [], "IIIMI": [], "IIIMM": [], "IIIMC": [], "IIICI": [], "IIICM": [], "IIICC": [], "IIMII": [], "IIMIM": [], "IIMIC": [], "IIMMI": [], "IIMMM": [], "IIMMC": [], "IIMCI": [], "IIMCM": [], "IIMCC": [], "IICII": [], "IICIM": [], "IICIC": [], "IICMI": [], "IICMM": [], "IICMC": [], "IICCI": [], "IICCM": [], "IICCC": [], "IMIII": [], "IMIIM": ["ENCES", "ESPES", "EXCES", "ESTES", "ESTEL", "ENTES", "EMPES", "EDEMA", "ELENC", "EFESI", "ENCEP", "EDETA", "ESPET", "EIXEA", "ENEMA", "ENCET", "ELEMI", "ENCEB"], "IMIIC": ["EXODE", "PLEXE", "ETILE", "ELAPE", "ABECE", "EPODE", "EPICE"], "IMIMI": [], "IMIMM": ["ESSER", "ENTER", "ESTER", "ESPER", "EIDER"], "IMIMC": ["CREPE"], "IMICI": [], "IMICM": ["ETERN", "ETERI", "ERERA", "EXERG"], "IMICC": ["ENTRE", "ESTRE", "EMPRE"], "IMMII": [], "IMMIM": [], "IMMIC": [], "IMMMI": [], "IMMMM": [], "IMMMC": [], "IMMCI": [], "IMMCM": [], "IMMCC": [], "IMCII": [], "IMCIM": [], "IMCIC": [], "IMCMI": [], "IMCMM": ["EGUER"], "IMCMC": [], "IMCCI": [], "IMCCM": [], "IMCCC": [], "ICIII": [], "ICIIM": ["DEMES", "GEMEC", "GENET", "SEMEN", "TEBEO", "TELEX", "SENET", "METEC", "DECES", "GELEA", "SENES", "SEDEC", "BETEL"], "ICIIC": ["SENSE", "SEGLE", "METGE", "FEBLE", "FETGE", "SETZE", "SETGE", "DELME", "PETGE", "BENZE", "CENTE", "SEPTE"], "ICIMI": [], "ICIMM": ["TEMER", "REMEI", "GENER", "REFER", "REBEL", "RECEL", "TELER", "RECER", "DELER", "RENEC", "FEMER", "REFET", "RECES", "REBEC", "REMER", "XERES", "REPEL", "SEDER", "PERER", "MENER", "CERER", "NERET", "RENET", "XEREC", "FENER", "PETER", "WEBER", "DENER", "REPES", "REGEL", "MELER"], "ICIMC": ["TERME", "SERIE", "REGNE", "MERCE", "RECTE", "REPTE", "REGLE", "REBLE", "REPLE", "PERXE", "TERPE"], "ICICI": [], "ICICM": [], "ICICC": ["REBRE", "NEGRE", "METRE", "FEBRE", "PEBRE", "RETRE", "GEBRE", "CEDRE", "FERRE", "TERRE"], "ICMII": [], "ICMIM": [], "ICMIC": ["TENUE"], "ICMMI": [], "ICMMM": ["HEREU", "REPEU", "REDEU"], "ICMMC": [], "ICMCI": [], "ICMCM": [], "ICMCC": [], "ICCII": [], "ICCIM": [], "ICCIC": ["DEUTE"], "ICCMI": [], "ICCMM": [], "ICCMC": [], "ICCCI": [], "ICCCM": [], "ICCCC": ["DEURE", "BEURE", "SEURE", "JEURE"], "MIIII": [], "MIIIM": [], "MIIIC": [], "MIIMI": [], "MIIMM": [], "MIIMC": [], "MIICI": [], "MIICM": [], "MIICC": [], "MIMII": [], "MIMIM": [], "MIMIC": [], "MIMMI": [], "MIMMM": [], "MIMMC": [], "MIMCI": [], "MIMCM": [], "MIMCC": [], "MICII": [], "MICIM": [], "MICIC": [], "MICMI": [], "MICMM": [], "MICMC": [], "MICCI": [], "MICCM": [], "MICCC": [], "MMIII": [], "MMIIM": [], "MMIIC": [], "MMIMI": [], "MMIMM": [], "MMIMC": [], "MMICI": [], "MMICM": [], "MMICC": [], "MMMII": [], "MMMIM": [], "MMMIC": [], "MMMMI": [], "MMMMM": [], "MMMMC": [], "MMMCI": [], "MMMCM": [], "MMMCC": [], "MMCII": [], "MMCIM": [], "MMCIC": [], "MMCMI": [], "MMCMM": [], "MMCMC": [], "MMCCI": [], "MMCCM": [], "MMCCC": [], "MCIII": [], "MCIIM": ["TEVET", "HEVEA"], "MCIIC": [], "MCIMI": [], "MCIMM": ["REVES", "SEVER"], "MCIMC": [], "MCICI": [], "MCICM": [], "MCICC": [], "MCMII": [], "MCMIM": [], "MCMIC": [], "MCMMI": [], "MCMMM": [], "MCMMC": [], "MCMCI": [], "MCMCM": [], "MCMCC": [], "MCCII": [], "MCCIM": [], "MCCIC": [], "MCCMI": [], "MCCMM": [], "MCCMC": [], "MCCCI": [], "MCCCM": [], "MCCCC": [], "CIIII": [], "CIIIM": [], "CIIIC": [], "CIIMI": [], "CIIMM": [], "CIIMC": [], "CIICI": [], "CIICM": [], "CIICC": [], "CIMII": [], "CIMIM": [], "CIMIC": [], "CIMMI": [], "CIMMM": [], "CIMMC": [], "CIMCI": [], "CIMCM": [], "CIMCC": [], "CICII": [], "CICIM": [], "CICIC": [], "CICMI": [], "CICMM": [], "CICMC": [], "CICCI": [], "CICCM": [], "CICCC": [], "CMIII": [], "CMIIM": [], "CMIIC": [], "CMIMI": [], "CMIMM": [], "CMIMC": [], "CMICI": [], "CMICM": [], "CMICC": [], "CMMII": [], "CMMIM": [], "CMMIC": [], "CMMMI": [], "CMMMM": [], "CMMMC": [], "CMMCI": [], "CMMCM": [], "CMMCC": [], "CMCII": [], "CMCIM": [], "CMCIC": [], "CMCMI": [], "CMCMM": [], "CMCMC": [], "CMCCI": [], "CMCCM": [], "CMCCC": [], "CCIII": [], "CCIIM": ["VEDET", "VENET"], "CCIIC": [], "CCIMI": [], "CCIMM": ["VELER"], "CCIMC": ["VERGE"], "CCICI": [], "CCICM": [], "CCICC": ["VEIRE"], "CCMII": [], "CCMIM": [], "CCMIC": [], "CCMMI": [], "CCMMM": [], "CCMMC": [], "CCMCI": [], "CCMCM": [], "CCMCC": [], "CCCII": [], "CCCIM": [], "CCCIC": [], "CCCMI": [], "CCCMM": [], "CCCMC": [], "CCCCI": [], "CCCCM": [], "CCCCC": ["VEURE"]}}